nco/__init__.py
nco/custom.py
nco/nco.py
nco-1.1.1.dist-info/LICENSE.txt
nco-1.1.1.dist-info/METADATA
nco-1.1.1.dist-info/WHEEL
nco-1.1.1.dist-info/top_level.txt
nco-1.1.1.dist-info/RECORD
