Metadata-Version: 2.1
Name: nco
Version: 1.1.1
Summary: python bindings to NCO
Author: Joe Hamman
Author-email: jhamman@ucar.edu
License: MIT
Project-URL: Source, https://github.com/nco/pynco
Project-URL: Documentation, https://pynco.readthedocs.org
Keywords: netcdf,climate
Classifier: Development Status :: 4 - Beta
Classifier: Topic :: Utilities
Classifier: Operating System :: POSIX
Classifier: Programming Language :: Python
Requires-Python: >=3.8
License-File: LICENSE.txt
Requires-Dist: numpy
Requires-Dist: packaging
